buzzheavier/__init__.py
buzzheavier/__main__.py
buzzheavier/buzz.py
buzzheavier-0.12.data/data/LICENSE.md
buzzheavier-0.12.data/data/README.md
buzzheavier-0.12.data/data/__version__.py
buzzheavier-0.12.dist-info/LICENSE.md
buzzheavier-0.12.dist-info/METADATA
buzzheavier-0.12.dist-info/WHEEL
buzzheavier-0.12.dist-info/entry_points.txt
buzzheavier-0.12.dist-info/top_level.txt
buzzheavier-0.12.dist-info/RECORD
